__init__.py
__main__.py
cli.py
json.py
ovh/__init__.py
ovh/api/__init__.py
ovh/api/dedicated.py
ovh/api/ip.py
ovh/cli.py
ovh/client.py
ovh/config.py
ovh/exceptions.py
ovh/manifests/__init__.py
ovh/manifests/base.py
ovh/manifests/ip.py
ovh/models/__init__.py
ovh/models/ip.py
bbrain.iac-0.1.0.dist-info/entry_points.txt
bbrain.iac-0.1.0.dist-info/WHEEL
bbrain.iac-0.1.0.dist-info/METADATA
bbrain.iac-0.1.0.dist-info/RECORD
