Metadata-Version: 2.1
Name: bbrain.iac
Version: 0.1.0
License: MIT
Author-email: Jonathan Scherrer <jonathan.s.scherrer@gmail.com>
Requires-Python: >=3.10
Requires-Dist: aiohttp>=3.8.1
Requires-Dist: click>=8.1.3
Requires-Dist: deepdiff>=5.8.1
Requires-Dist: flatten-dict>=0.4.2
Requires-Dist: paramiko>=2.12.0
Requires-Dist: pygments>=2.13.0
Requires-Dist: python-json-logger>=2.0.4
Requires-Dist: ruamel.yaml>=0.17.21
